odoo9_addon_crm_phone-9.0.1.0.0.99.dev12-py3.8-nspkg.pth
odoo_addons/crm_phone/__init__.py
odoo_addons/crm_phone/__openerp__.py
odoo_addons/crm_phone/crm_phone.py
odoo_addons/crm_phone/demo/crm_phonecall.xml
odoo_addons/crm_phone/i18n/fr.po
odoo_addons/crm_phone/i18n/sl.po
odoo_addons/crm_phone/security/ir.model.access.csv
odoo_addons/crm_phone/security/phonecall_security.xml
odoo_addons/crm_phone/static/description/icon.png
odoo_addons/crm_phone/tests/__init__.py
odoo_addons/crm_phone/tests/test_crm_phone.py
odoo_addons/crm_phone/view/crm_lead.xml
odoo_addons/crm_phone/view/crm_phonecall.xml
odoo_addons/crm_phone/view/res_partner.xml
odoo_addons/crm_phone/view/res_users.xml
odoo_addons/crm_phone/wizard/__init__.py
odoo_addons/crm_phone/wizard/create_crm_phonecall.py
odoo_addons/crm_phone/wizard/create_crm_phonecall_view.xml
odoo_addons/crm_phone/wizard/number_not_found.py
odoo_addons/crm_phone/wizard/number_not_found_view.xml
odoo9_addon_crm_phone-9.0.1.0.0.99.dev12.dist-info/METADATA
odoo9_addon_crm_phone-9.0.1.0.0.99.dev12.dist-info/WHEEL
odoo9_addon_crm_phone-9.0.1.0.0.99.dev12.dist-info/namespace_packages.txt
odoo9_addon_crm_phone-9.0.1.0.0.99.dev12.dist-info/top_level.txt
odoo9_addon_crm_phone-9.0.1.0.0.99.dev12.dist-info/RECORD
